astrovision/__init__.py
astrovision/data/__init__.py
astrovision/data/constants.py
astrovision/data/labeled_satellite_image.py
astrovision/data/satellite_image.py
astrovision/data/utils.py
astrovision/filter/__init__.py
astrovision/filter/bounds.py
astrovision/filter/clouds.py
astrovision/filter/corruption.py
astrovision/plot/__init__.py
astrovision/plot/plot_utils.py
astrovision/sample/__init__.py
astrovision/sample/sample.py
astrovision-0.14.7.dist-info/LICENSE
astrovision-0.14.7.dist-info/METADATA
astrovision-0.14.7.dist-info/WHEEL
astrovision-0.14.7.dist-info/RECORD
